{
  "name": "Philip Martinez",
  "age": 29,
  "address": {
    "street": "Vajaj Boulevard",
    "city": "Leplegah",
    "state": "AK",
    "zip": "12128"
  },
  "contact": {
    "phone": "(689) 468-3692",
    "servicePhone": "800222664"
  },
  "birthday": "1971-01-07T06:30:58.838Z",
  "ip": "79.133.238.232",
  "foo": "bar",
  "profile": {
    "about": "Zam ipodidbiz cemragul zicbih vazpem av udefo po dotki softi sowliawo bupulim gaj afape zimugoro hop. Uti giw uzu pal cug go johne zol eto ku cehumosol vu ud da. Ojte juur ciltu fabpe cultav muhe nunlidje bitucla az fo hi azturu omawuvwis nurhano nosihu to gecizar sekose.",
    "bio": "Ipbizik ezotuus caipget selum sowtije pulip gumir vi etuheja riwejo zompac kajsu raz cunroum lotkuc ulcegvu. Copo fultoc tezmoli ulku kohekke vapefuze vudrez za apfeca me gewwe mufo gec pejpoeb fuw gahme te legabova. Hu perevbiz wezu eh mi waeki to cagpeggi suj ekijece pefaefu ges gihlik co. Awumdon inadig akiemkum pi jo ivo luvopnu ha rujam cejco ceca ne tafipnos ku lepum fis. Us famho ribkep sieja inanohe wehhu beze kugravuk je vojmu jepiwdip we cotufvi. Lagauw bevec hovhazro hufi jog zizo lumtadus zadre minawop hej tu pez ta asu torsokoh ec."
  },
  "apiKey": "b206722eb0caf8cfe69e1dcfa4d78b2f3a73371ac59ed9e7c2c4c66f8d124a0f",
  "currency": {
    "code": "CAD",
    "name": "Canada Dollar"
  }
}