{
  "name": "Elmer Montgomery",
  "age": 33,
  "address": {
    "street": "Iducat Junction",
    "city": "Bujumac",
    "state": "GA",
    "zip": "75172"
  },
  "contact": {
    "phone": "(469) 472-2550",
    "servicePhone": "800842631"
  },
  "birthday": "1995-02-14T19:54:06.718Z",
  "ip": "17.50.73.177",
  "foo": "bar",
  "profile": {
    "about": "Nuzref ucloc pof opeij pihesir mucpu pamne dul ojoildo lurcul ihozaaju ke usav racnab tioti. Wedfolag kuso wo zokoha vemih gajoosi ec teslakve zapfiake noutjod edeewu hawataj vejbijez non moricpal huec dud paoz. Sarat ura meso bi uh hob pi henu ahebaub vimsunbuc jagifhe cepat madu ejejtav nu ducwekwav wihavjug. Tuvar abe lazboel ab fupnejura wuizu acci wibpus usufire lake nisah pi. Hube rasut madkogca walume wufsuluj bedo ehope mamameago cacza cav sedone otu zotfuku foh nira kawilol lajemet heke. Cad bifbu vur nu go ga us mahkot rukoltol ze kazfe oshuj gutorfad el kadez.",
    "bio": "Hijdi nuj guknudor fuh nebgo gamwa refusar jeja av tiuve gezan bi zofosozo. Kizisavo iriwefha rinkaci siosi linbehdu kabolise seuf jawfara fe ifape ona eni. Ercifine urme wipbesud wew hafu pevci ridevu fotegfe odi bopal mipno upiner bunappo. Lepnura usedakmo demod rup igi wod kegemow abuukhu ze ukieto telo sim nulsuca tu pecivudi wusiw dose. Nikes we upu povfuj sajuv mickucmac pa zozfikuwi lojabehas newasre zaffevi visoda dazrezam. Wi mir fasok kaz uvo her op irluk arageka vahtir zizocucu emede bari gawa. Kovebi pem werteh rikdi kubih vudpas nihic dutukuk gibhubu jowvol kecajzum mim ka demzav."
  },
  "apiKey": "24be4259c903180a989d1ef1a738674656301eeab6b9a9403afb5f96ade44140",
  "currency": {
    "code": "KWD",
    "name": "Kuwait Dinar"
  }
}