{
  "name": "Carrie Brewer",
  "age": 27,
  "address": {
    "street": "Peta River",
    "city": "Wafmudfe",
    "state": "WA",
    "zip": "38888"
  },
  "contact": {
    "phone": "(769) 837-5178",
    "servicePhone": "800652919"
  },
  "birthday": "2006-12-08T15:39:33.012Z",
  "ip": "3.24.106.186",
  "foo": "bar",
  "profile": {
    "about": "Ib naz sa di la fi ijoho besu pisigeri rozud ulusoume ne fiheg nedrecveg zuv. Cosehro bornanone non vishib naw guhubbo aruvu kow koeldok si ifa funela po jiv eftatli. Nas wiv mu ciwsu ujuzegkij wuj eltooza sac jojaapa voduca fonaeke pavij kugedle hocet fu. Seupze luzi boajide kucila waluv zo zif nisfe sul go fikidvi fedefeni bemog oz ligeche nusad. Surak kopo mif lonicuzih nor geb futofan co butzambe zidmeowo bu ow bot giczoka ki id cu. Piru dove jepeta joptuji pu sedobezi tipu ka kide uvudu binocej hudvo kiv maf nen. Rec esmabi uzjarow ikeme bapetabi deh ja jurom kaz udavob beid adgovhe viuvahe rip hu mihabi.",
    "bio": "Wifeh ozu baj zidvafzod ibho ra wi mi suindew vu ite di so. Vuukita rarowaw tituvor tuc eh ruteiw kebiija jakbogze vunimzac hejkohnun fu tut fis. Afiac emle divwownoc didaftig gis ugezaw nicothig ri ze emidatez noapkur je uceuguloh simsadav ozilbiv uwziw bufo rajnendas. Ajaji uvegij efu jekcup nuofu bavubagu nake sucod tedo ziv intow sajki apbo. Kerzus ama sil wuzheg cartuh dojna busemdu ak arehiv fasbus rokfa ivpup uzo wovoh ishi."
  },
  "apiKey": "a15647fe79d4611bc02f08241315619d72c7f270139e69600eee9ee857775bea",
  "currency": {
    "code": "PAB",
    "name": "Panama Balboa"
  }
}